INSTALL.rst
LICENSE
MANIFEST.in
README.rst
VERSION
requirements.txt
setup.py
tasks.py
src/kpop/__init__.py
src/kpop/__main__.py
src/kpop/__meta__.py
src/kpop/individual.py
src/kpop/population.py
src/kpop/probability_distribution.py
src/kpop/structure.py
src/kpop/structure_params.py
src/kpop.egg-info/PKG-INFO
src/kpop.egg-info/SOURCES.txt
src/kpop.egg-info/dependency_links.txt
src/kpop.egg-info/not-zip-safe
src/kpop.egg-info/requires.txt
src/kpop.egg-info/top_level.txt
src/kpop/tests/__init__.py
src/kpop/tests/__main__.py
src/kpop/tests/conftest.py
src/kpop/tests/test_documentation.py
src/kpop/tests/test_individual.py
src/kpop/tests/test_structure.py